spaceone/__init__.py
spaceone/file_manager/__init__.py
spaceone/file_manager/conf/__init__.py
spaceone/file_manager/conf/global_conf.py
spaceone/file_manager/conf/router_conf.py
spaceone/file_manager/connector/__init__.py
spaceone/file_manager/connector/aws_s3_connector.py
spaceone/file_manager/connector/file_base_connector.py
spaceone/file_manager/error/__init__.py
spaceone/file_manager/error/custom.py
spaceone/file_manager/interface/__init__.py
spaceone/file_manager/interface/grpc/__init__.py
spaceone/file_manager/interface/grpc/file.py
spaceone/file_manager/interface/rest/__init__.py
spaceone/file_manager/interface/rest/files.py
spaceone/file_manager/interface/rest/users.py
spaceone/file_manager/manager/__init__.py
spaceone/file_manager/manager/file_connector_manager.py
spaceone/file_manager/manager/file_manager.py
spaceone/file_manager/manager/identity_manager.py
spaceone/file_manager/model/__init__.py
spaceone/file_manager/model/file/__init__.py
spaceone/file_manager/model/file/database.py
spaceone/file_manager/model/file/request.py
spaceone/file_manager/model/file/response.py
spaceone/file_manager/service/__init__.py
spaceone/file_manager/service/file_service.py
spaceone_file_manager-2.0.0.dist-info/METADATA
spaceone_file_manager-2.0.0.dist-info/WHEEL
spaceone_file_manager-2.0.0.dist-info/top_level.txt
spaceone_file_manager-2.0.0.dist-info/RECORD
