Metadata-Version: 2.1
Name: spaceone-file-manager
Version: 2.0.0
Summary: SpaceONE file manager service
Home-page: https://www.spaceone.dev/
Author: MEGAZONE SpaceONE Team
Author-email: admin@spaceone.dev
License: Apache License 2.0
Platform: UNKNOWN
Requires-Dist: spaceone-core
Requires-Dist: spaceone-api
Requires-Dist: python-multipart
